doctortest/__init__.py
doctortest-1.0.1.dist-info/licenses/LICENSE
doctortest-1.0.1.dist-info/METADATA
doctortest-1.0.1.dist-info/WHEEL
doctortest-1.0.1.dist-info/top_level.txt
doctortest-1.0.1.dist-info/RECORD
